rio/__init__.py
rio/__main__.py
rio/app.py
rio/arequests.py
rio/assets.py
rio/byte_serving.py
rio/color.py
rio/component_meta.py
rio/cursor_style.py
rio/data_models.py
rio/deprecations.py
rio/dialog.py
rio/docs.py
rio/errors.py
rio/event.py
rio/extension.py
rio/extension_event.py
rio/fills.py
rio/global_state.py
rio/icon_registry.py
rio/icons.py
rio/inspection.py
rio/language_info.py
rio/maybes.py
rio/nice_traceback.py
rio/path_match.py
rio/project_config.py
rio/py.typed
rio/routing.py
rio/self_serializing.py
rio/serialization.py
rio/session.py
rio/text_style.py
rio/theme.py
rio/url_pattern.py
rio/user_settings_module.py
rio/utils.py
rio/version.py
rio/warnings.py
rio/weak_key_id_default_dict.py
rio/webview_shim.py
rio/app_server/__init__.py
rio/app_server/abstract_app_server.py
rio/app_server/fastapi_server.py
rio/app_server/testing_server.py
rio/assets/fonts/Roboto/LICENSE.txt
rio/assets/fonts/Roboto/Roboto-Bold.ttf
rio/assets/fonts/Roboto/Roboto-BoldItalic.ttf
rio/assets/fonts/Roboto/Roboto-Italic.ttf
rio/assets/fonts/Roboto/Roboto-Regular.ttf
rio/assets/fonts/Roboto Mono/LICENSE.txt
rio/assets/fonts/Roboto Mono/RobotoMono-Bold.ttf
rio/assets/fonts/Roboto Mono/RobotoMono-BoldItalic.ttf
rio/assets/fonts/Roboto Mono/RobotoMono-Italic.ttf
rio/assets/fonts/Roboto Mono/RobotoMono-Regular.ttf
rio/assets/hosted/README.md
rio/assets/hosted/rio_logos/logo_and_text_horizontal.png
rio/assets/hosted/rio_logos/rio_logo_square.png
rio/assets/icon_sets/brand.tar.xz
rio/assets/icon_sets/material.tar.xz
rio/assets/icon_sets/rio.tar.xz
rio/assets/icon_sets/styling.tar.xz
rio/cli/__init__.py
rio/cli/cloud_commands.py
rio/cli/project_setup.py
rio/cli/run_project/__init__.py
rio/cli/run_project/app_loading.py
rio/cli/run_project/arbiter.py
rio/cli/run_project/file_watcher_worker.py
rio/cli/run_project/run_models.py
rio/cli/run_project/uvicorn_worker.py
rio/cli/run_project/webview_worker.py
rio/components/__init__.py
rio/components/app_root.py
rio/components/auto_form.py
rio_ui-0.12.dist-info/METADATA
rio_ui-0.12.dist-info/WHEEL
rio_ui-0.12.dist-info/entry_points.txt
rio_ui-0.12.dist-info/licenses/LICENSE.txt
rio_ui-0.12.dist-info/RECORD
