Metadata-Version: 2.4
Name: rio-ui
Version: 0.12
Summary: Build modern Websites and Apps just with Python
Project-URL: homepage, https://rio.dev
Project-URL: repository, https://github.com/rio-labs/rio
Project-URL: documentation, https://rio.dev/docs
Author-email: Jakob Pinterits <jakob.pinterits@gmail.com>, Paul Pinterits <rawing7@gmail.com>
License: Apache License
License-File: LICENSE.txt
Keywords: app,framework,functional,local-app,modern,react,rio,type-safe,typed,typing,user-interface,web,web-app,web-development,web-framework
Classifier: Development Status :: 4 - Beta
Classifier: Intended Audience :: Developers
Classifier: Intended Audience :: Financial and Insurance Industry
Classifier: Intended Audience :: Information Technology
Classifier: License :: OSI Approved :: Apache Software License
Classifier: Operating System :: OS Independent
Classifier: Programming Language :: Python :: 3
Classifier: Programming Language :: Python :: 3.10
Classifier: Programming Language :: Python :: 3.11
Classifier: Programming Language :: Python :: 3.12
Classifier: Programming Language :: Python :: 3.13
Classifier: Topic :: Internet :: WWW/HTTP :: Dynamic Content
Classifier: Topic :: Internet :: WWW/HTTP :: WSGI :: Application
Classifier: Topic :: Software Development :: Libraries :: Python Modules
Requires-Python: >=3.10
Requires-Dist: crawlerdetect<0.4,>=0.1.7
Requires-Dist: cssutils<3.0,>=2.11.1
Requires-Dist: fastapi<0.129,>=0.110
Requires-Dist: gitignore-parser<0.2,>=0.1.11
Requires-Dist: identity-containers<2.0,>=1.0.2
Requires-Dist: imy[deprecations,docstrings]<0.8,>=0.7.1
Requires-Dist: introspection<2.0,>=1.11.1
Requires-Dist: isort<8.0,>=5.13
Requires-Dist: langcodes<4.0,>=3.4
Requires-Dist: multipart<2.0,>=1.2
Requires-Dist: narwhals<3.0,>=1.13
Requires-Dist: ordered-set<5.0,>=4.1
Requires-Dist: path-imports<2.0,>=1.1.2
Requires-Dist: pillow<13.0,>=10.2
Requires-Dist: platformdirs<5.0,>=4.3
Requires-Dist: pytz>=2024.1
Requires-Dist: rapidfuzz<4.0,>=3.12.2
Requires-Dist: revel<0.10,>=0.9.2post1
Requires-Dist: timer-dict<2.0,>=1.0
Requires-Dist: tomlkit<0.14,>=0.12
Requires-Dist: typing-extensions<5.0,>=4.5
Requires-Dist: unicall<0.3,>=0.2post0
Requires-Dist: uniserde<0.5,>=0.4.1
Requires-Dist: uvicorn[standard]<0.41,>=0.29.0
Requires-Dist: watchfiles<2.0,>=0.21
Requires-Dist: yarl<2.0,>=1.9
Provides-Extra: window
Requires-Dist: aiofiles<26.0,>=24.1; extra == 'window'
Requires-Dist: copykitten<3.0,>=1.2; extra == 'window'
Requires-Dist: pyside6<=6.7.3; (python_version < '3.13') and extra == 'window'
Requires-Dist: pywebview[pyside6]<7.0,>=6.0; extra == 'window'
